README.rst
setup.py
Pynoramio.egg-info/PKG-INFO
Pynoramio.egg-info/SOURCES.txt
Pynoramio.egg-info/dependency_links.txt
Pynoramio.egg-info/requires.txt
Pynoramio.egg-info/top_level.txt
pynoramio/__init__.py