Metadata-Version: 1.1
Name: Pynoramio
Version: 0.1
Summary: Python SDK for the Panoramio data API (http://panoramio.com/api/data/api.html)
Home-page: https://github.com/boisei0/pynoramio
Author: Rob Derksen
Author-email: rob.derksen@hubsec.eu
License: MIT
Keywords: api maps panoramio
Platform: UNKNOWN
Classifier: Development Status :: 4 - Beta
Classifier: Intended Audience :: Developers
Classifier: License :: OSI Approved :: MIT License
Classifier: Programming Language :: Python :: 2.7
